massbots/__init__.py
massbots/api.py
massbots/error.py
massbots/models.py
massbots-1.1.0.dist-info/LICENSE
massbots-1.1.0.dist-info/METADATA
massbots-1.1.0.dist-info/WHEEL
massbots-1.1.0.dist-info/RECORD
